{
  "apple": {
    "N": {
      "min": 10.0,
      "max": 30.0
    },
    "P": {
      "min": 127.5,
      "max": 141.5
    },
    "K": {
      "min": 197.0,
      "max": 203.0
    },
    "temperature": {
      "min": 22.16,
      "max": 23.34
    },
    "humidity": {
      "min": 90.96,
      "max": 93.48
    },
    "ph": {
      "min": 5.7,
      "max": 6.14
    },
    "rainfall": {
      "min": 106.0,
      "max": 118.06
    }
  },
  "banana": {
    "N": {
      "min": 92.0,
      "max": 108.5
    },
    "P": {
      "min": 75.0,
      "max": 88.0
    },
    "K": {
      "min": 47.0,
      "max": 53.0
    },
    "temperature": {
      "min": 26.09,
      "max": 28.66
    },
    "humidity": {
      "min": 78.06,
      "max": 82.96
    },
    "ph": {
      "min": 5.74,
      "max": 6.21
    },
    "rainfall": {
      "min": 96.46,
      "max": 112.07
    }
  },
  "blackgram": {
    "N": {
      "min": 28.25,
      "max": 52.0
    },
    "P": {
      "min": 62.0,
      "max": 74.0
    },
    "K": {
      "min": 16.25,
      "max": 22.0
    },
    "temperature": {
      "min": 27.82,
      "max": 32.23
    },
    "humidity": {
      "min": 63.04,
      "max": 67.71
    },
    "ph": {
      "min": 6.81,
      "max": 7.42
    },
    "rainfall": {
      "min": 63.79,
      "max": 71.4
    }
  },
  "chickpea": {
    "N": {
      "min": 30.0,
      "max": 52.0
    },
    "P": {
      "min": 61.0,
      "max": 73.75
    },
    "K": {
      "min": 77.0,
      "max": 83.0
    },
    "temperature": {
      "min": 17.91,
      "max": 19.7
    },
    "humidity": {
      "min": 15.4,
      "max": 18.43
    },
    "ph": {
      "min": 6.62,
      "max": 7.89
    },
    "rainfall": {
      "min": 73.64,
      "max": 85.58
    }
  },
  "coconut": {
    "N": {
      "min": 13.75,
      "max": 31.0
    },
    "P": {
      "min": 9.75,
      "max": 24.25
    },
    "K": {
      "min": 29.0,
      "max": 33.0
    },
    "temperature": {
      "min": 26.24,
      "max": 28.63
    },
    "humidity": {
      "min": 92.51,
      "max": 96.87
    },
    "ph": {
      "min": 5.74,
      "max": 6.21
    },
    "rainfall": {
      "min": 149.03,
      "max": 200.85
    }
  },
  "coffee": {
    "N": {
      "min": 89.0,
      "max": 112.0
    },
    "P": {
      "min": 23.0,
      "max": 34.5
    },
    "K": {
      "min": 27.0,
      "max": 33.0
    },
    "temperature": {
      "min": 24.24,
      "max": 26.77
    },
    "humidity": {
      "min": 53.74,
      "max": 63.55
    },
    "ph": {
      "min": 6.43,
      "max": 7.11
    },
    "rainfall": {
      "min": 135.11,
      "max": 181.47
    }
  },
  "cotton": {
    "N": {
      "min": 107.75,
      "max": 127.5
    },
    "P": {
      "min": 40.0,
      "max": 52.0
    },
    "K": {
      "min": 17.0,
      "max": 22.0
    },
    "temperature": {
      "min": 23.04,
      "max": 24.99
    },
    "humidity": {
      "min": 77.0,
      "max": 82.31
    },
    "ph": {
      "min": 6.39,
      "max": 7.43
    },
    "rainfall": {
      "min": 70.82,
      "max": 90.25
    }
  },
  "grapes": {
    "N": {
      "min": 11.75,
      "max": 35.0
    },
    "P": {
      "min": 125.75,
      "max": 139.0
    },
    "K": {
      "min": 197.0,
      "max": 203.0
    },
    "temperature": {
      "min": 16.32,
      "max": 30.92
    },
    "humidity": {
      "min": 80.86,
      "max": 82.85
    },
    "ph": {
      "min": 5.78,
      "max": 6.31
    },
    "rainfall": {
      "min": 66.84,
      "max": 71.61
    }
  },
  "kidneybeans": {
    "N": {
      "min": 11.5,
      "max": 28.0
    },
    "P": {
      "min": 61.0,
      "max": 74.0
    },
    "K": {
      "min": 17.0,
      "max": 22.5
    },
    "temperature": {
      "min": 18.27,
      "max": 21.94
    },
    "humidity": {
      "min": 19.74,
      "max": 23.48
    },
    "ph": {
      "min": 5.62,
      "max": 5.87
    },
    "rainfall": {
      "min": 87.05,
      "max": 129.57
    }
  },
  "lentil": {
    "N": {
      "min": 9.0,
      "max": 29.5
    },
    "P": {
      "min": 61.5,
      "max": 74.5
    },
    "K": {
      "min": 17.0,
      "max": 22.0
    },
    "temperature": {
      "min": 21.8,
      "max": 27.48
    },
    "humidity": {
      "min": 62.46,
      "max": 67.34
    },
    "ph": {
      "min": 6.49,
      "max": 7.39
    },
    "rainfall": {
      "min": 41.45,
      "max": 50.17
    }
  },
  "maize": {
    "N": {
      "min": 67.5,
      "max": 87.0
    },
    "P": {
      "min": 42.5,
      "max": 55.5
    },
    "K": {
      "min": 17.0,
      "max": 22.0
    },
    "temperature": {
      "min": 19.77,
      "max": 24.91
    },
    "humidity": {
      "min": 60.51,
      "max": 69.57
    },
    "ph": {
      "min": 5.86,
      "max": 6.61
    },
    "rainfall": {
      "min": 70.76,
      "max": 100.17
    }
  },
  "mango": {
    "N": {
      "min": 9.0,
      "max": 30.5
    },
    "P": {
      "min": 20.0,
      "max": 35.0
    },
    "K": {
      "min": 27.0,
      "max": 32.0
    },
    "temperature": {
      "min": 28.91,
      "max": 33.35
    },
    "humidity": {
      "min": 47.92,
      "max": 52.49
    },
    "ph": {
      "min": 5.18,
      "max": 6.42
    },
    "rainfall": {
      "min": 91.59,
      "max": 97.46
    }
  },
  "mothbeans": {
    "N": {
      "min": 11.0,
      "max": 31.0
    },
    "P": {
      "min": 43.0,
      "max": 55.0
    },
    "K": {
      "min": 18.0,
      "max": 23.0
    },
    "temperature": {
      "min": 26.34,
      "max": 30.24
    },
    "humidity": {
      "min": 46.92,
      "max": 59.14
    },
    "ph": {
      "min": 5.34,
      "max": 8.47
    },
    "rainfall": {
      "min": 37.65,
      "max": 64.04
    }
  },
  "mungbean": {
    "N": {
      "min": 10.0,
      "max": 31.0
    },
    "P": {
      "min": 40.0,
      "max": 55.0
    },
    "K": {
      "min": 17.0,
      "max": 22.0
    },
    "temperature": {
      "min": 27.91,
      "max": 29.26
    },
    "humidity": {
      "min": 83.53,
      "max": 87.91
    },
    "ph": {
      "min": 6.46,
      "max": 6.98
    },
    "rainfall": {
      "min": 43.13,
      "max": 55.02
    }
  },
  "muskmelon": {
    "N": {
      "min": 89.0,
      "max": 111.0
    },
    "P": {
      "min": 12.0,
      "max": 25.0
    },
    "K": {
      "min": 47.0,
      "max": 52.25
    },
    "temperature": {
      "min": 27.94,
      "max": 29.43
    },
    "humidity": {
      "min": 90.96,
      "max": 93.79
    },
    "ph": {
      "min": 6.16,
      "max": 6.55
    },
    "rainfall": {
      "min": 22.06,
      "max": 26.85
    }
  },
  "orange": {
    "N": {
      "min": 9.0,
      "max": 31.0
    },
    "P": {
      "min": 9.0,
      "max": 23.0
    },
    "K": {
      "min": 8.0,
      "max": 12.5
    },
    "temperature": {
      "min": 17.05,
      "max": 29.55
    },
    "humidity": {
      "min": 91.03,
      "max": 93.37
    },
    "ph": {
      "min": 6.48,
      "max": 7.52
    },
    "rainfall": {
      "min": 106.17,
      "max": 115.57
    }
  },
  "papaya": {
    "N": {
      "min": 39.0,
      "max": 59.25
    },
    "P": {
      "min": 54.0,
      "max": 65.0
    },
    "K": {
      "min": 47.0,
      "max": 52.0
    },
    "temperature": {
      "min": 28.46,
      "max": 39.13
    },
    "humidity": {
      "min": 91.16,
      "max": 93.54
    },
    "ph": {
      "min": 6.62,
      "max": 6.84
    },
    "rainfall": {
      "min": 81.94,
      "max": 202.39
    }
  },
  "pigeonpeas": {
    "N": {
      "min": 10.0,
      "max": 30.0
    },
    "P": {
      "min": 61.0,
      "max": 73.0
    },
    "K": {
      "min": 18.0,
      "max": 23.0
    },
    "temperature": {
      "min": 22.35,
      "max": 31.47
    },
    "humidity": {
      "min": 38.11,
      "max": 57.0
    },
    "ph": {
      "min": 5.0,
      "max": 6.43
    },
    "rainfall": {
      "min": 122.46,
      "max": 177.58
    }
  },
  "pomegranate": {
    "N": {
      "min": 8.0,
      "max": 29.25
    },
    "P": {
      "min": 13.0,
      "max": 25.0
    },
    "K": {
      "min": 38.0,
      "max": 42.5
    },
    "temperature": {
      "min": 19.83,
      "max": 23.89
    },
    "humidity": {
      "min": 88.1,
      "max": 92.43
    },
    "ph": {
      "min": 6.0,
      "max": 6.89
    },
    "rainfall": {
      "min": 104.92,
      "max": 110.05
    }
  },
  "rice": {
    "N": {
      "min": 69.0,
      "max": 91.0
    },
    "P": {
      "min": 41.0,
      "max": 54.25
    },
    "K": {
      "min": 38.0,
      "max": 42.0
    },
    "temperature": {
      "min": 21.97,
      "max": 25.51
    },
    "humidity": {
      "min": 80.95,
      "max": 83.47
    },
    "ph": {
      "min": 5.87,
      "max": 7.04
    },
    "rainfall": {
      "min": 204.6,
      "max": 264.13
    }
  },
  "watermelon": {
    "N": {
      "min": 89.0,
      "max": 110.0
    },
    "P": {
      "min": 10.0,
      "max": 23.0
    },
    "K": {
      "min": 47.0,
      "max": 53.0
    },
    "temperature": {
      "min": 24.9,
      "max": 26.27
    },
    "humidity": {
      "min": 82.98,
      "max": 87.65
    },
    "ph": {
      "min": 6.26,
      "max": 6.76
    },
    "rainfall": {
      "min": 46.06,
      "max": 56.43
    }
  }
}